odooss/__init__.py
odooss/cli.py
odooss/main.py
odooss/utils.py
odooss/folder_structure/__init__.py
odooss/folder_structure/docker.py
odooss/folder_structure/gitignore.py
odooss/folder_structure/requirements.py
odooss/folder_structure/ruff.py
odooss/folder_structure/tools.py
odooss/precommit/__init__.py
odooss/precommit/precommit_config.py
odooss/vcs/__init__.py
odooss/vcs/github_workflow.py
odooss-1.0.2.dist-info/licenses/LICENSE
odooss-1.0.2.dist-info/METADATA
odooss-1.0.2.dist-info/WHEEL
odooss-1.0.2.dist-info/entry_points.txt
odooss-1.0.2.dist-info/top_level.txt
odooss-1.0.2.dist-info/RECORD
