Metadata-Version: 2.4
Name: odooss
Version: 1.0.2
Summary: IdeaCode Academy Odoo Standard Structure — starting point repo.
Author-email: Agga <hanzawnyineonline@gmail.com>
Project-URL: Homepage, https://github.com/HanZawNyein/ica_standard_structure.git
Project-URL: Repository, https://github.com/HanZawNyein/ica_standard_structure.git
Requires-Python: >=3.10
License-File: LICENSE
Requires-Dist: click>=8.2.1
Dynamic: license-file
